{"nodes": [{"id": "c_users_agnivad_onedrive_microsoft_agniva_starter_agent_os_tests_unit_ccp_artifacts_io_test_ts", "label": "io.test.ts", "file_type": "code", "source_file": "C:\\Users\\agnivad\\OneDrive - Microsoft\\Agniva\\starter\\Agent_OS\\tests\\unit\\ccp\\artifacts\\io.test.ts", "source_location": "L1"}, {"id": "artifacts_io_test_dir", "label": "dir", "file_type": "code", "source_file": "C:\\Users\\agnivad\\OneDrive - Microsoft\\Agniva\\starter\\Agent_OS\\tests\\unit\\ccp\\artifacts\\io.test.ts", "source_location": "L11"}, {"id": "artifacts_io_test_env", "label": "env", "file_type": "code", "source_file": "C:\\Users\\agnivad\\OneDrive - Microsoft\\Agniva\\starter\\Agent_OS\\tests\\unit\\ccp\\artifacts\\io.test.ts", "source_location": "L13"}, {"id": "artifacts_io_test_record", "label": "record", "file_type": "code", "source_file": "C:\\Users\\agnivad\\OneDrive - Microsoft\\Agniva\\starter\\Agent_OS\\tests\\unit\\ccp\\artifacts\\io.test.ts", "source_location": "L14"}, {"id": "artifacts_io_test_back", "label": "back", "file_type": "code", "source_file": "C:\\Users\\agnivad\\OneDrive - Microsoft\\Agniva\\starter\\Agent_OS\\tests\\unit\\ccp\\artifacts\\io.test.ts", "source_location": "L28"}, {"id": "artifacts_io_test_bad", "label": "bad", "file_type": "code", "source_file": "C:\\Users\\agnivad\\OneDrive - Microsoft\\Agniva\\starter\\Agent_OS\\tests\\unit\\ccp\\artifacts\\io.test.ts", "source_location": "L36"}], "edges": [{"source": "c_users_agnivad_onedrive_microsoft_agniva_starter_agent_os_tests_unit_ccp_artifacts_io_test_ts", "target": "node_fs", "relation": "imports_from", "context": "import", "confidence": "EXTRACTED", "source_file": "C:\\Users\\agnivad\\OneDrive - Microsoft\\Agniva\\starter\\Agent_OS\\tests\\unit\\ccp\\artifacts\\io.test.ts", "source_location": "L1", "weight": 1.0}, {"source": "c_users_agnivad_onedrive_microsoft_agniva_starter_agent_os_tests_unit_ccp_artifacts_io_test_ts", "target": "node_os", "relation": "imports_from", "context": "import", "confidence": "EXTRACTED", "source_file": "C:\\Users\\agnivad\\OneDrive - Microsoft\\Agniva\\starter\\Agent_OS\\tests\\unit\\ccp\\artifacts\\io.test.ts", "source_location": "L2", "weight": 1.0}, {"source": "c_users_agnivad_onedrive_microsoft_agniva_starter_agent_os_tests_unit_ccp_artifacts_io_test_ts", "target": "node_path", "relation": "imports_from", "context": "import", "confidence": "EXTRACTED", "source_file": "C:\\Users\\agnivad\\OneDrive - Microsoft\\Agniva\\starter\\Agent_OS\\tests\\unit\\ccp\\artifacts\\io.test.ts", "source_location": "L3", "weight": 1.0}, {"source": "c_users_agnivad_onedrive_microsoft_agniva_starter_agent_os_tests_unit_ccp_artifacts_io_test_ts", "target": "vitest", "relation": "imports_from", "context": "import", "confidence": "EXTRACTED", "source_file": "C:\\Users\\agnivad\\OneDrive - Microsoft\\Agniva\\starter\\Agent_OS\\tests\\unit\\ccp\\artifacts\\io.test.ts", "source_location": "L5", "weight": 1.0}, {"source": "c_users_agnivad_onedrive_microsoft_agniva_starter_agent_os_tests_unit_ccp_artifacts_io_test_ts", "target": "c_users_agnivad_onedrive_microsoft_agniva_starter_agent_os_src_ccp_artifacts_envelope_ts", "relation": "imports_from", "context": "import", "confidence": "EXTRACTED", "source_file": "C:\\Users\\agnivad\\OneDrive - Microsoft\\Agniva\\starter\\Agent_OS\\tests\\unit\\ccp\\artifacts\\io.test.ts", "source_location": "L6", "weight": 1.0}, {"source": "c_users_agnivad_onedrive_microsoft_agniva_starter_agent_os_tests_unit_ccp_artifacts_io_test_ts", "target": "artifacts_envelope_makeenvelope", "relation": "imports", "context": "import", "confidence": "EXTRACTED", "source_file": "C:\\Users\\agnivad\\OneDrive - Microsoft\\Agniva\\starter\\Agent_OS\\tests\\unit\\ccp\\artifacts\\io.test.ts", "source_location": "L6", "weight": 1.0}, {"source": "c_users_agnivad_onedrive_microsoft_agniva_starter_agent_os_tests_unit_ccp_artifacts_io_test_ts", "target": "c_users_agnivad_onedrive_microsoft_agniva_starter_agent_os_src_ccp_artifacts_io_ts", "relation": "imports_from", "context": "import", "confidence": "EXTRACTED", "source_file": "C:\\Users\\agnivad\\OneDrive - Microsoft\\Agniva\\starter\\Agent_OS\\tests\\unit\\ccp\\artifacts\\io.test.ts", "source_location": "L7", "weight": 1.0}, {"source": "c_users_agnivad_onedrive_microsoft_agniva_starter_agent_os_tests_unit_ccp_artifacts_io_test_ts", "target": "artifacts_io_readartifact", "relation": "imports", "context": "import", "confidence": "EXTRACTED", "source_file": "C:\\Users\\agnivad\\OneDrive - Microsoft\\Agniva\\starter\\Agent_OS\\tests\\unit\\ccp\\artifacts\\io.test.ts", "source_location": "L7", "weight": 1.0}, {"source": "c_users_agnivad_onedrive_microsoft_agniva_starter_agent_os_tests_unit_ccp_artifacts_io_test_ts", "target": "artifacts_io_writeartifact", "relation": "imports", "context": "import", "confidence": "EXTRACTED", "source_file": "C:\\Users\\agnivad\\OneDrive - Microsoft\\Agniva\\starter\\Agent_OS\\tests\\unit\\ccp\\artifacts\\io.test.ts", "source_location": "L7", "weight": 1.0}, {"source": "c_users_agnivad_onedrive_microsoft_agniva_starter_agent_os_tests_unit_ccp_artifacts_io_test_ts", "target": "artifacts_io_test_dir", "relation": "contains", "confidence": "EXTRACTED", "source_file": "C:\\Users\\agnivad\\OneDrive - Microsoft\\Agniva\\starter\\Agent_OS\\tests\\unit\\ccp\\artifacts\\io.test.ts", "source_location": "L11", "weight": 1.0}, {"source": "c_users_agnivad_onedrive_microsoft_agniva_starter_agent_os_tests_unit_ccp_artifacts_io_test_ts", "target": "artifacts_io_test_env", "relation": "contains", "confidence": "EXTRACTED", "source_file": "C:\\Users\\agnivad\\OneDrive - Microsoft\\Agniva\\starter\\Agent_OS\\tests\\unit\\ccp\\artifacts\\io.test.ts", "source_location": "L13", "weight": 1.0}, {"source": "c_users_agnivad_onedrive_microsoft_agniva_starter_agent_os_tests_unit_ccp_artifacts_io_test_ts", "target": "artifacts_io_test_record", "relation": "contains", "confidence": "EXTRACTED", "source_file": "C:\\Users\\agnivad\\OneDrive - Microsoft\\Agniva\\starter\\Agent_OS\\tests\\unit\\ccp\\artifacts\\io.test.ts", "source_location": "L14", "weight": 1.0}, {"source": "c_users_agnivad_onedrive_microsoft_agniva_starter_agent_os_tests_unit_ccp_artifacts_io_test_ts", "target": "artifacts_io_test_back", "relation": "contains", "confidence": "EXTRACTED", "source_file": "C:\\Users\\agnivad\\OneDrive - Microsoft\\Agniva\\starter\\Agent_OS\\tests\\unit\\ccp\\artifacts\\io.test.ts", "source_location": "L28", "weight": 1.0}, {"source": "c_users_agnivad_onedrive_microsoft_agniva_starter_agent_os_tests_unit_ccp_artifacts_io_test_ts", "target": "artifacts_io_test_dir", "relation": "contains", "confidence": "EXTRACTED", "source_file": "C:\\Users\\agnivad\\OneDrive - Microsoft\\Agniva\\starter\\Agent_OS\\tests\\unit\\ccp\\artifacts\\io.test.ts", "source_location": "L34", "weight": 1.0}, {"source": "c_users_agnivad_onedrive_microsoft_agniva_starter_agent_os_tests_unit_ccp_artifacts_io_test_ts", "target": "artifacts_io_test_bad", "relation": "contains", "confidence": "EXTRACTED", "source_file": "C:\\Users\\agnivad\\OneDrive - Microsoft\\Agniva\\starter\\Agent_OS\\tests\\unit\\ccp\\artifacts\\io.test.ts", "source_location": "L36", "weight": 1.0}, {"source": "c_users_agnivad_onedrive_microsoft_agniva_starter_agent_os_tests_unit_ccp_artifacts_io_test_ts", "target": "artifacts_io_test_dir", "relation": "contains", "confidence": "EXTRACTED", "source_file": "C:\\Users\\agnivad\\OneDrive - Microsoft\\Agniva\\starter\\Agent_OS\\tests\\unit\\ccp\\artifacts\\io.test.ts", "source_location": "L41", "weight": 1.0}], "raw_calls": []}