{"nodes": [{"id": "c_users_agnivad_onedrive_microsoft_agniva_starter_agent_os_src_ccp_commands_evaluate_ts", "label": "evaluate.ts", "file_type": "code", "source_file": "C:\\Users\\agnivad\\OneDrive - Microsoft\\Agniva\\starter\\Agent_OS\\src\\ccp\\commands\\evaluate.ts", "source_location": "L1"}, {"id": "commands_evaluate_taskoutcome", "label": "TaskOutcome", "file_type": "code", "source_file": "C:\\Users\\agnivad\\OneDrive - Microsoft\\Agniva\\starter\\Agent_OS\\src\\ccp\\commands\\evaluate.ts", "source_location": "L9"}, {"id": "commands_evaluate_processquality", "label": "ProcessQuality", "file_type": "code", "source_file": "C:\\Users\\agnivad\\OneDrive - Microsoft\\Agniva\\starter\\Agent_OS\\src\\ccp\\commands\\evaluate.ts", "source_location": "L10"}, {"id": "commands_evaluate_evaluateargs", "label": "EvaluateArgs", "file_type": "code", "source_file": "C:\\Users\\agnivad\\OneDrive - Microsoft\\Agniva\\starter\\Agent_OS\\src\\ccp\\commands\\evaluate.ts", "source_location": "L12"}, {"id": "commands_evaluate_evaluateresult", "label": "EvaluateResult", "file_type": "code", "source_file": "C:\\Users\\agnivad\\OneDrive - Microsoft\\Agniva\\starter\\Agent_OS\\src\\ccp\\commands\\evaluate.ts", "source_location": "L19"}, {"id": "commands_evaluate_runevaluate", "label": "runEvaluate()", "file_type": "code", "source_file": "C:\\Users\\agnivad\\OneDrive - Microsoft\\Agniva\\starter\\Agent_OS\\src\\ccp\\commands\\evaluate.ts", "source_location": "L25"}], "edges": [{"source": "c_users_agnivad_onedrive_microsoft_agniva_starter_agent_os_src_ccp_commands_evaluate_ts", "target": "c_users_agnivad_onedrive_microsoft_agniva_starter_agent_os_src_core_projector_ts", "relation": "imports_from", "context": "import", "confidence": "EXTRACTED", "source_file": "C:\\Users\\agnivad\\OneDrive - Microsoft\\Agniva\\starter\\Agent_OS\\src\\ccp\\commands\\evaluate.ts", "source_location": "L1", "weight": 1.0}, {"source": "c_users_agnivad_onedrive_microsoft_agniva_starter_agent_os_src_ccp_commands_evaluate_ts", "target": "core_projector_emitandproject", "relation": "imports", "context": "import", "confidence": "EXTRACTED", "source_file": "C:\\Users\\agnivad\\OneDrive - Microsoft\\Agniva\\starter\\Agent_OS\\src\\ccp\\commands\\evaluate.ts", "source_location": "L1", "weight": 1.0}, {"source": "c_users_agnivad_onedrive_microsoft_agniva_starter_agent_os_src_ccp_commands_evaluate_ts", "target": "c_users_agnivad_onedrive_microsoft_agniva_starter_agent_os_src_pi_ui_ts", "relation": "imports_from", "context": "import", "confidence": "EXTRACTED", "source_file": "C:\\Users\\agnivad\\OneDrive - Microsoft\\Agniva\\starter\\Agent_OS\\src\\ccp\\commands\\evaluate.ts", "source_location": "L2", "weight": 1.0}, {"source": "c_users_agnivad_onedrive_microsoft_agniva_starter_agent_os_src_ccp_commands_evaluate_ts", "target": "pi_ui_uiadapter", "relation": "imports", "context": "import", "confidence": "EXTRACTED", "source_file": "C:\\Users\\agnivad\\OneDrive - Microsoft\\Agniva\\starter\\Agent_OS\\src\\ccp\\commands\\evaluate.ts", "source_location": "L2", "weight": 1.0}, {"source": "c_users_agnivad_onedrive_microsoft_agniva_starter_agent_os_src_ccp_commands_evaluate_ts", "target": "c_users_agnivad_onedrive_microsoft_agniva_starter_agent_os_src_ccp_artifacts_envelope_ts", "relation": "imports_from", "context": "import", "confidence": "EXTRACTED", "source_file": "C:\\Users\\agnivad\\OneDrive - Microsoft\\Agniva\\starter\\Agent_OS\\src\\ccp\\commands\\evaluate.ts", "source_location": "L3", "weight": 1.0}, {"source": "c_users_agnivad_onedrive_microsoft_agniva_starter_agent_os_src_ccp_commands_evaluate_ts", "target": "artifacts_envelope_makeenvelope", "relation": "imports", "context": "import", "confidence": "EXTRACTED", "source_file": "C:\\Users\\agnivad\\OneDrive - Microsoft\\Agniva\\starter\\Agent_OS\\src\\ccp\\commands\\evaluate.ts", "source_location": "L3", "weight": 1.0}, {"source": "c_users_agnivad_onedrive_microsoft_agniva_starter_agent_os_src_ccp_commands_evaluate_ts", "target": "c_users_agnivad_onedrive_microsoft_agniva_starter_agent_os_src_ccp_artifacts_io_ts", "relation": "imports_from", "context": "import", "confidence": "EXTRACTED", "source_file": "C:\\Users\\agnivad\\OneDrive - Microsoft\\Agniva\\starter\\Agent_OS\\src\\ccp\\commands\\evaluate.ts", "source_location": "L4", "weight": 1.0}, {"source": "c_users_agnivad_onedrive_microsoft_agniva_starter_agent_os_src_ccp_commands_evaluate_ts", "target": "artifacts_io_readartifactraw", "relation": "imports", "context": "import", "confidence": "EXTRACTED", "source_file": "C:\\Users\\agnivad\\OneDrive - Microsoft\\Agniva\\starter\\Agent_OS\\src\\ccp\\commands\\evaluate.ts", "source_location": "L4", "weight": 1.0}, {"source": "c_users_agnivad_onedrive_microsoft_agniva_starter_agent_os_src_ccp_commands_evaluate_ts", "target": "artifacts_io_writeartifact", "relation": "imports", "context": "import", "confidence": "EXTRACTED", "source_file": "C:\\Users\\agnivad\\OneDrive - Microsoft\\Agniva\\starter\\Agent_OS\\src\\ccp\\commands\\evaluate.ts", "source_location": "L4", "weight": 1.0}, {"source": "c_users_agnivad_onedrive_microsoft_agniva_starter_agent_os_src_ccp_commands_evaluate_ts", "target": "c_users_agnivad_onedrive_microsoft_agniva_starter_agent_os_src_ccp_ccp_events_ts", "relation": "imports_from", "context": "import", "confidence": "EXTRACTED", "source_file": "C:\\Users\\agnivad\\OneDrive - Microsoft\\Agniva\\starter\\Agent_OS\\src\\ccp\\commands\\evaluate.ts", "source_location": "L5", "weight": 1.0}, {"source": "c_users_agnivad_onedrive_microsoft_agniva_starter_agent_os_src_ccp_commands_evaluate_ts", "target": "ccp_ccp_events_buildevaluatecompletedevent", "relation": "imports", "context": "import", "confidence": "EXTRACTED", "source_file": "C:\\Users\\agnivad\\OneDrive - Microsoft\\Agniva\\starter\\Agent_OS\\src\\ccp\\commands\\evaluate.ts", "source_location": "L5", "weight": 1.0}, {"source": "c_users_agnivad_onedrive_microsoft_agniva_starter_agent_os_src_ccp_commands_evaluate_ts", "target": "ccp_ccp_events_buildevaluatestartedevent", "relation": "imports", "context": "import", "confidence": "EXTRACTED", "source_file": "C:\\Users\\agnivad\\OneDrive - Microsoft\\Agniva\\starter\\Agent_OS\\src\\ccp\\commands\\evaluate.ts", "source_location": "L5", "weight": 1.0}, {"source": "c_users_agnivad_onedrive_microsoft_agniva_starter_agent_os_src_ccp_commands_evaluate_ts", "target": "c_users_agnivad_onedrive_microsoft_agniva_starter_agent_os_src_ccp_task_paths_ts", "relation": "imports_from", "context": "import", "confidence": "EXTRACTED", "source_file": "C:\\Users\\agnivad\\OneDrive - Microsoft\\Agniva\\starter\\Agent_OS\\src\\ccp\\commands\\evaluate.ts", "source_location": "L6", "weight": 1.0}, {"source": "c_users_agnivad_onedrive_microsoft_agniva_starter_agent_os_src_ccp_commands_evaluate_ts", "target": "ccp_task_paths_taskartifactpath", "relation": "imports", "context": "import", "confidence": "EXTRACTED", "source_file": "C:\\Users\\agnivad\\OneDrive - Microsoft\\Agniva\\starter\\Agent_OS\\src\\ccp\\commands\\evaluate.ts", "source_location": "L6", "weight": 1.0}, {"source": "c_users_agnivad_onedrive_microsoft_agniva_starter_agent_os_src_ccp_commands_evaluate_ts", "target": "c_users_agnivad_onedrive_microsoft_agniva_starter_agent_os_src_ccp_commands_shared_task_lifecycle_ts", "relation": "imports_from", "context": "import", "confidence": "EXTRACTED", "source_file": "C:\\Users\\agnivad\\OneDrive - Microsoft\\Agniva\\starter\\Agent_OS\\src\\ccp\\commands\\evaluate.ts", "source_location": "L7", "weight": 1.0}, {"source": "c_users_agnivad_onedrive_microsoft_agniva_starter_agent_os_src_ccp_commands_evaluate_ts", "target": "shared_task_lifecycle_transitiontasklifecycle", "relation": "imports", "context": "import", "confidence": "EXTRACTED", "source_file": "C:\\Users\\agnivad\\OneDrive - Microsoft\\Agniva\\starter\\Agent_OS\\src\\ccp\\commands\\evaluate.ts", "source_location": "L7", "weight": 1.0}, {"source": "c_users_agnivad_onedrive_microsoft_agniva_starter_agent_os_src_ccp_commands_evaluate_ts", "target": "commands_evaluate_taskoutcome", "relation": "contains", "confidence": "EXTRACTED", "source_file": "C:\\Users\\agnivad\\OneDrive - Microsoft\\Agniva\\starter\\Agent_OS\\src\\ccp\\commands\\evaluate.ts", "source_location": "L9", "weight": 1.0}, {"source": "c_users_agnivad_onedrive_microsoft_agniva_starter_agent_os_src_ccp_commands_evaluate_ts", "target": "commands_evaluate_processquality", "relation": "contains", "confidence": "EXTRACTED", "source_file": "C:\\Users\\agnivad\\OneDrive - Microsoft\\Agniva\\starter\\Agent_OS\\src\\ccp\\commands\\evaluate.ts", "source_location": "L10", "weight": 1.0}, {"source": "c_users_agnivad_onedrive_microsoft_agniva_starter_agent_os_src_ccp_commands_evaluate_ts", "target": "commands_evaluate_evaluateargs", "relation": "contains", "confidence": "EXTRACTED", "source_file": "C:\\Users\\agnivad\\OneDrive - Microsoft\\Agniva\\starter\\Agent_OS\\src\\ccp\\commands\\evaluate.ts", "source_location": "L12", "weight": 1.0}, {"source": "c_users_agnivad_onedrive_microsoft_agniva_starter_agent_os_src_ccp_commands_evaluate_ts", "target": "commands_evaluate_evaluateresult", "relation": "contains", "confidence": "EXTRACTED", "source_file": "C:\\Users\\agnivad\\OneDrive - Microsoft\\Agniva\\starter\\Agent_OS\\src\\ccp\\commands\\evaluate.ts", "source_location": "L19", "weight": 1.0}, {"source": "c_users_agnivad_onedrive_microsoft_agniva_starter_agent_os_src_ccp_commands_evaluate_ts", "target": "commands_evaluate_runevaluate", "relation": "contains", "confidence": "EXTRACTED", "source_file": "C:\\Users\\agnivad\\OneDrive - Microsoft\\Agniva\\starter\\Agent_OS\\src\\ccp\\commands\\evaluate.ts", "source_location": "L25", "weight": 1.0}], "raw_calls": [{"caller_nid": "commands_evaluate_runevaluate", "callee": "transitionTaskLifecycle", "is_member_call": false, "source_file": "C:\\Users\\agnivad\\OneDrive - Microsoft\\Agniva\\starter\\Agent_OS\\src\\ccp\\commands\\evaluate.ts", "source_location": "L26"}, {"caller_nid": "commands_evaluate_runevaluate", "callee": "emitAndProject", "is_member_call": false, "source_file": "C:\\Users\\agnivad\\OneDrive - Microsoft\\Agniva\\starter\\Agent_OS\\src\\ccp\\commands\\evaluate.ts", "source_location": "L40"}, {"caller_nid": "commands_evaluate_runevaluate", "callee": "buildEvaluateStartedEvent", "is_member_call": false, "source_file": "C:\\Users\\agnivad\\OneDrive - Microsoft\\Agniva\\starter\\Agent_OS\\src\\ccp\\commands\\evaluate.ts", "source_location": "L43"}, {"caller_nid": "commands_evaluate_runevaluate", "callee": "readArtifact", "is_member_call": false, "source_file": "C:\\Users\\agnivad\\OneDrive - Microsoft\\Agniva\\starter\\Agent_OS\\src\\ccp\\commands\\evaluate.ts", "source_location": "L50"}, {"caller_nid": "commands_evaluate_runevaluate", "callee": "isArray", "is_member_call": true, "source_file": "C:\\Users\\agnivad\\OneDrive - Microsoft\\Agniva\\starter\\Agent_OS\\src\\ccp\\commands\\evaluate.ts", "source_location": "L52"}, {"caller_nid": "commands_evaluate_runevaluate", "callee": "readArtifact", "is_member_call": false, "source_file": "C:\\Users\\agnivad\\OneDrive - Microsoft\\Agniva\\starter\\Agent_OS\\src\\ccp\\commands\\evaluate.ts", "source_location": "L55"}, {"caller_nid": "commands_evaluate_runevaluate", "callee": "readArtifact", "is_member_call": false, "source_file": "C:\\Users\\agnivad\\OneDrive - Microsoft\\Agniva\\starter\\Agent_OS\\src\\ccp\\commands\\evaluate.ts", "source_location": "L61"}, {"caller_nid": "commands_evaluate_runevaluate", "callee": "round", "is_member_call": true, "source_file": "C:\\Users\\agnivad\\OneDrive - Microsoft\\Agniva\\starter\\Agent_OS\\src\\ccp\\commands\\evaluate.ts", "source_location": "L78"}, {"caller_nid": "commands_evaluate_runevaluate", "callee": "max", "is_member_call": true, "source_file": "C:\\Users\\agnivad\\OneDrive - Microsoft\\Agniva\\starter\\Agent_OS\\src\\ccp\\commands\\evaluate.ts", "source_location": "L78"}, {"caller_nid": "commands_evaluate_runevaluate", "callee": "confirm", "is_member_call": true, "source_file": "C:\\Users\\agnivad\\OneDrive - Microsoft\\Agniva\\starter\\Agent_OS\\src\\ccp\\commands\\evaluate.ts", "source_location": "L79"}, {"caller_nid": "commands_evaluate_runevaluate", "callee": "round", "is_member_call": true, "source_file": "C:\\Users\\agnivad\\OneDrive - Microsoft\\Agniva\\starter\\Agent_OS\\src\\ccp\\commands\\evaluate.ts", "source_location": "L80"}, {"caller_nid": "commands_evaluate_runevaluate", "callee": "select", "is_member_call": true, "source_file": "C:\\Users\\agnivad\\OneDrive - Microsoft\\Agniva\\starter\\Agent_OS\\src\\ccp\\commands\\evaluate.ts", "source_location": "L83"}, {"caller_nid": "commands_evaluate_runevaluate", "callee": "select", "is_member_call": true, "source_file": "C:\\Users\\agnivad\\OneDrive - Microsoft\\Agniva\\starter\\Agent_OS\\src\\ccp\\commands\\evaluate.ts", "source_location": "L90"}, {"caller_nid": "commands_evaluate_runevaluate", "callee": "input", "is_member_call": true, "source_file": "C:\\Users\\agnivad\\OneDrive - Microsoft\\Agniva\\starter\\Agent_OS\\src\\ccp\\commands\\evaluate.ts", "source_location": "L97"}, {"caller_nid": "commands_evaluate_runevaluate", "callee": "makeEnvelope", "is_member_call": false, "source_file": "C:\\Users\\agnivad\\OneDrive - Microsoft\\Agniva\\starter\\Agent_OS\\src\\ccp\\commands\\evaluate.ts", "source_location": "L99"}, {"caller_nid": "commands_evaluate_runevaluate", "callee": "writeArtifact", "is_member_call": false, "source_file": "C:\\Users\\agnivad\\OneDrive - Microsoft\\Agniva\\starter\\Agent_OS\\src\\ccp\\commands\\evaluate.ts", "source_location": "L100"}, {"caller_nid": "commands_evaluate_runevaluate", "callee": "emitAndProject", "is_member_call": false, "source_file": "C:\\Users\\agnivad\\OneDrive - Microsoft\\Agniva\\starter\\Agent_OS\\src\\ccp\\commands\\evaluate.ts", "source_location": "L112"}, {"caller_nid": "commands_evaluate_runevaluate", "callee": "buildEvaluateCompletedEvent", "is_member_call": false, "source_file": "C:\\Users\\agnivad\\OneDrive - Microsoft\\Agniva\\starter\\Agent_OS\\src\\ccp\\commands\\evaluate.ts", "source_location": "L115"}, {"caller_nid": "commands_evaluate_runevaluate", "callee": "transitionTaskLifecycle", "is_member_call": false, "source_file": "C:\\Users\\agnivad\\OneDrive - Microsoft\\Agniva\\starter\\Agent_OS\\src\\ccp\\commands\\evaluate.ts", "source_location": "L124"}, {"caller_nid": "commands_evaluate_runevaluate", "callee": "taskArtifactPath", "is_member_call": false, "source_file": "C:\\Users\\agnivad\\OneDrive - Microsoft\\Agniva\\starter\\Agent_OS\\src\\ccp\\commands\\evaluate.ts", "source_location": "L136"}]}