{"nodes": [{"id": "c_users_agnivad_onedrive_microsoft_agniva_starter_agent_os_src_core_renderer_ts", "label": "renderer.ts", "file_type": "code", "source_file": "C:\\Users\\agnivad\\OneDrive - Microsoft\\Agniva\\starter\\Agent_OS\\src\\core\\renderer.ts", "source_location": "L1"}, {"id": "core_renderer_codes", "label": "CODES", "file_type": "code", "source_file": "C:\\Users\\agnivad\\OneDrive - Microsoft\\Agniva\\starter\\Agent_OS\\src\\core\\renderer.ts", "source_location": "L20"}, {"id": "core_renderer_c", "label": "c()", "file_type": "code", "source_file": "C:\\Users\\agnivad\\OneDrive - Microsoft\\Agniva\\starter\\Agent_OS\\src\\core\\renderer.ts", "source_location": "L30"}, {"id": "core_renderer_health_color", "label": "HEALTH_COLOR", "file_type": "code", "source_file": "C:\\Users\\agnivad\\OneDrive - Microsoft\\Agniva\\starter\\Agent_OS\\src\\core\\renderer.ts", "source_location": "L37"}, {"id": "core_renderer_healthline", "label": "healthLine()", "file_type": "code", "source_file": "C:\\Users\\agnivad\\OneDrive - Microsoft\\Agniva\\starter\\Agent_OS\\src\\core\\renderer.ts", "source_location": "L45"}, {"id": "core_renderer_packversionstate", "label": "PackVersionState", "file_type": "code", "source_file": "C:\\Users\\agnivad\\OneDrive - Microsoft\\Agniva\\starter\\Agent_OS\\src\\core\\renderer.ts", "source_location": "L56"}, {"id": "core_renderer_pack_glyph", "label": "PACK_GLYPH", "file_type": "code", "source_file": "C:\\Users\\agnivad\\OneDrive - Microsoft\\Agniva\\starter\\Agent_OS\\src\\core\\renderer.ts", "source_location": "L58"}, {"id": "core_renderer_renderpackbadge", "label": "renderPackBadge()", "file_type": "code", "source_file": "C:\\Users\\agnivad\\OneDrive - Microsoft\\Agniva\\starter\\Agent_OS\\src\\core\\renderer.ts", "source_location": "L66"}, {"id": "core_renderer_renderprogressbar", "label": "renderProgressBar()", "file_type": "code", "source_file": "C:\\Users\\agnivad\\OneDrive - Microsoft\\Agniva\\starter\\Agent_OS\\src\\core\\renderer.ts", "source_location": "L83"}, {"id": "core_renderer_validatoroutcome", "label": "ValidatorOutcome", "file_type": "code", "source_file": "C:\\Users\\agnivad\\OneDrive - Microsoft\\Agniva\\starter\\Agent_OS\\src\\core\\renderer.ts", "source_location": "L100"}, {"id": "core_renderer_rendervalidatorsummary", "label": "renderValidatorSummary()", "file_type": "code", "source_file": "C:\\Users\\agnivad\\OneDrive - Microsoft\\Agniva\\starter\\Agent_OS\\src\\core\\renderer.ts", "source_location": "L107"}, {"id": "core_renderer_rendermemorystate", "label": "renderMemoryState()", "file_type": "code", "source_file": "C:\\Users\\agnivad\\OneDrive - Microsoft\\Agniva\\starter\\Agent_OS\\src\\core\\renderer.ts", "source_location": "L123"}, {"id": "core_renderer_show", "label": "SHOW", "file_type": "code", "source_file": "C:\\Users\\agnivad\\OneDrive - Microsoft\\Agniva\\starter\\Agent_OS\\src\\core\\renderer.ts", "source_location": "L131"}, {"id": "core_renderer_filtered", "label": "filtered()", "file_type": "code", "source_file": "C:\\Users\\agnivad\\OneDrive - Microsoft\\Agniva\\starter\\Agent_OS\\src\\core\\renderer.ts", "source_location": "L155"}, {"id": "core_renderer_row", "label": "row()", "file_type": "code", "source_file": "C:\\Users\\agnivad\\OneDrive - Microsoft\\Agniva\\starter\\Agent_OS\\src\\core\\renderer.ts", "source_location": "L159"}, {"id": "core_renderer_renderstatusopts", "label": "RenderStatusOpts", "file_type": "code", "source_file": "C:\\Users\\agnivad\\OneDrive - Microsoft\\Agniva\\starter\\Agent_OS\\src\\core\\renderer.ts", "source_location": "L167"}, {"id": "core_renderer_renderstatustostring", "label": "renderStatusToString()", "file_type": "code", "source_file": "C:\\Users\\agnivad\\OneDrive - Microsoft\\Agniva\\starter\\Agent_OS\\src\\core\\renderer.ts", "source_location": "L172"}, {"id": "core_renderer_rendertraceopts", "label": "RenderTraceOpts", "file_type": "code", "source_file": "C:\\Users\\agnivad\\OneDrive - Microsoft\\Agniva\\starter\\Agent_OS\\src\\core\\renderer.ts", "source_location": "L227"}, {"id": "core_renderer_rendertracetostring", "label": "renderTraceToString()", "file_type": "code", "source_file": "C:\\Users\\agnivad\\OneDrive - Microsoft\\Agniva\\starter\\Agent_OS\\src\\core\\renderer.ts", "source_location": "L232"}, {"id": "core_renderer_writereportmd", "label": "writeReportMd()", "file_type": "code", "source_file": "C:\\Users\\agnivad\\OneDrive - Microsoft\\Agniva\\starter\\Agent_OS\\src\\core\\renderer.ts", "source_location": "L276"}, {"id": "core_renderer_findmostrecentsession", "label": "findMostRecentSession()", "file_type": "code", "source_file": "C:\\Users\\agnivad\\OneDrive - Microsoft\\Agniva\\starter\\Agent_OS\\src\\core\\renderer.ts", "source_location": "L323"}, {"id": "core_renderer_loadsessiondashboard", "label": "loadSessionDashboard()", "file_type": "code", "source_file": "C:\\Users\\agnivad\\OneDrive - Microsoft\\Agniva\\starter\\Agent_OS\\src\\core\\renderer.ts", "source_location": "L339"}], "edges": [{"source": "c_users_agnivad_onedrive_microsoft_agniva_starter_agent_os_src_core_renderer_ts", "target": "node_fs", "relation": "imports_from", "context": "import", "confidence": "EXTRACTED", "source_file": "C:\\Users\\agnivad\\OneDrive - Microsoft\\Agniva\\starter\\Agent_OS\\src\\core\\renderer.ts", "source_location": "L1", "weight": 1.0}, {"source": "c_users_agnivad_onedrive_microsoft_agniva_starter_agent_os_src_core_renderer_ts", "target": "node_path", "relation": "imports_from", "context": "import", "confidence": "EXTRACTED", "source_file": "C:\\Users\\agnivad\\OneDrive - Microsoft\\Agniva\\starter\\Agent_OS\\src\\core\\renderer.ts", "source_location": "L8", "weight": 1.0}, {"source": "c_users_agnivad_onedrive_microsoft_agniva_starter_agent_os_src_core_renderer_ts", "target": "c_users_agnivad_onedrive_microsoft_agniva_starter_agent_os_src_core_projector_ts", "relation": "imports_from", "context": "import", "confidence": "EXTRACTED", "source_file": "C:\\Users\\agnivad\\OneDrive - Microsoft\\Agniva\\starter\\Agent_OS\\src\\core\\renderer.ts", "source_location": "L9", "weight": 1.0}, {"source": "c_users_agnivad_onedrive_microsoft_agniva_starter_agent_os_src_core_renderer_ts", "target": "core_projector_sessiondashboard", "relation": "imports", "context": "import", "confidence": "EXTRACTED", "source_file": "C:\\Users\\agnivad\\OneDrive - Microsoft\\Agniva\\starter\\Agent_OS\\src\\core\\renderer.ts", "source_location": "L9", "weight": 1.0}, {"source": "c_users_agnivad_onedrive_microsoft_agniva_starter_agent_os_src_core_renderer_ts", "target": "core_projector_timelineentry", "relation": "imports", "context": "import", "confidence": "EXTRACTED", "source_file": "C:\\Users\\agnivad\\OneDrive - Microsoft\\Agniva\\starter\\Agent_OS\\src\\core\\renderer.ts", "source_location": "L9", "weight": 1.0}, {"source": "c_users_agnivad_onedrive_microsoft_agniva_starter_agent_os_src_core_renderer_ts", "target": "c_users_agnivad_onedrive_microsoft_agniva_starter_agent_os_src_core_health_ts", "relation": "imports_from", "context": "import", "confidence": "EXTRACTED", "source_file": "C:\\Users\\agnivad\\OneDrive - Microsoft\\Agniva\\starter\\Agent_OS\\src\\core\\renderer.ts", "source_location": "L10", "weight": 1.0}, {"source": "c_users_agnivad_onedrive_microsoft_agniva_starter_agent_os_src_core_renderer_ts", "target": "core_health_healthstatus", "relation": "imports", "context": "import", "confidence": "EXTRACTED", "source_file": "C:\\Users\\agnivad\\OneDrive - Microsoft\\Agniva\\starter\\Agent_OS\\src\\core\\renderer.ts", "source_location": "L10", "weight": 1.0}, {"source": "c_users_agnivad_onedrive_microsoft_agniva_starter_agent_os_src_core_renderer_ts", "target": "core_health_agelabel", "relation": "imports", "context": "import", "confidence": "EXTRACTED", "source_file": "C:\\Users\\agnivad\\OneDrive - Microsoft\\Agniva\\starter\\Agent_OS\\src\\core\\renderer.ts", "source_location": "L10", "weight": 1.0}, {"source": "c_users_agnivad_onedrive_microsoft_agniva_starter_agent_os_src_core_renderer_ts", "target": "core_health_classifyhealth", "relation": "imports", "context": "import", "confidence": "EXTRACTED", "source_file": "C:\\Users\\agnivad\\OneDrive - Microsoft\\Agniva\\starter\\Agent_OS\\src\\core\\renderer.ts", "source_location": "L10", "weight": 1.0}, {"source": "c_users_agnivad_onedrive_microsoft_agniva_starter_agent_os_src_core_renderer_ts", "target": "core_health_timelabel", "relation": "imports", "context": "import", "confidence": "EXTRACTED", "source_file": "C:\\Users\\agnivad\\OneDrive - Microsoft\\Agniva\\starter\\Agent_OS\\src\\core\\renderer.ts", "source_location": "L10", "weight": 1.0}, {"source": "c_users_agnivad_onedrive_microsoft_agniva_starter_agent_os_src_core_renderer_ts", "target": "c_users_agnivad_onedrive_microsoft_agniva_starter_agent_os_src_core_runtime_paths_ts", "relation": "imports_from", "context": "import", "confidence": "EXTRACTED", "source_file": "C:\\Users\\agnivad\\OneDrive - Microsoft\\Agniva\\starter\\Agent_OS\\src\\core\\renderer.ts", "source_location": "L11", "weight": 1.0}, {"source": "c_users_agnivad_onedrive_microsoft_agniva_starter_agent_os_src_core_renderer_ts", "target": "core_runtime_paths_runtimedir", "relation": "imports", "context": "import", "confidence": "EXTRACTED", "source_file": "C:\\Users\\agnivad\\OneDrive - Microsoft\\Agniva\\starter\\Agent_OS\\src\\core\\renderer.ts", "source_location": "L11", "weight": 1.0}, {"source": "c_users_agnivad_onedrive_microsoft_agniva_starter_agent_os_src_core_renderer_ts", "target": "core_runtime_paths_sessiondashboardpath", "relation": "imports", "context": "import", "confidence": "EXTRACTED", "source_file": "C:\\Users\\agnivad\\OneDrive - Microsoft\\Agniva\\starter\\Agent_OS\\src\\core\\renderer.ts", "source_location": "L11", "weight": 1.0}, {"source": "c_users_agnivad_onedrive_microsoft_agniva_starter_agent_os_src_core_renderer_ts", "target": "core_renderer_codes", "relation": "contains", "confidence": "EXTRACTED", "source_file": "C:\\Users\\agnivad\\OneDrive - Microsoft\\Agniva\\starter\\Agent_OS\\src\\core\\renderer.ts", "source_location": "L20", "weight": 1.0}, {"source": "c_users_agnivad_onedrive_microsoft_agniva_starter_agent_os_src_core_renderer_ts", "target": "core_renderer_c", "relation": "contains", "confidence": "EXTRACTED", "source_file": "C:\\Users\\agnivad\\OneDrive - Microsoft\\Agniva\\starter\\Agent_OS\\src\\core\\renderer.ts", "source_location": "L30", "weight": 1.0}, {"source": "c_users_agnivad_onedrive_microsoft_agniva_starter_agent_os_src_core_renderer_ts", "target": "core_renderer_health_color", "relation": "contains", "confidence": "EXTRACTED", "source_file": "C:\\Users\\agnivad\\OneDrive - Microsoft\\Agniva\\starter\\Agent_OS\\src\\core\\renderer.ts", "source_location": "L37", "weight": 1.0}, {"source": "c_users_agnivad_onedrive_microsoft_agniva_starter_agent_os_src_core_renderer_ts", "target": "core_renderer_healthline", "relation": "contains", "confidence": "EXTRACTED", "source_file": "C:\\Users\\agnivad\\OneDrive - Microsoft\\Agniva\\starter\\Agent_OS\\src\\core\\renderer.ts", "source_location": "L45", "weight": 1.0}, {"source": "c_users_agnivad_onedrive_microsoft_agniva_starter_agent_os_src_core_renderer_ts", "target": "core_renderer_packversionstate", "relation": "contains", "confidence": "EXTRACTED", "source_file": "C:\\Users\\agnivad\\OneDrive - Microsoft\\Agniva\\starter\\Agent_OS\\src\\core\\renderer.ts", "source_location": "L56", "weight": 1.0}, {"source": "c_users_agnivad_onedrive_microsoft_agniva_starter_agent_os_src_core_renderer_ts", "target": "core_renderer_pack_glyph", "relation": "contains", "confidence": "EXTRACTED", "source_file": "C:\\Users\\agnivad\\OneDrive - Microsoft\\Agniva\\starter\\Agent_OS\\src\\core\\renderer.ts", "source_location": "L58", "weight": 1.0}, {"source": "c_users_agnivad_onedrive_microsoft_agniva_starter_agent_os_src_core_renderer_ts", "target": "core_renderer_renderpackbadge", "relation": "contains", "confidence": "EXTRACTED", "source_file": "C:\\Users\\agnivad\\OneDrive - Microsoft\\Agniva\\starter\\Agent_OS\\src\\core\\renderer.ts", "source_location": "L66", "weight": 1.0}, {"source": "c_users_agnivad_onedrive_microsoft_agniva_starter_agent_os_src_core_renderer_ts", "target": "core_renderer_renderprogressbar", "relation": "contains", "confidence": "EXTRACTED", "source_file": "C:\\Users\\agnivad\\OneDrive - Microsoft\\Agniva\\starter\\Agent_OS\\src\\core\\renderer.ts", "source_location": "L83", "weight": 1.0}, {"source": "c_users_agnivad_onedrive_microsoft_agniva_starter_agent_os_src_core_renderer_ts", "target": "core_renderer_validatoroutcome", "relation": "contains", "confidence": "EXTRACTED", "source_file": "C:\\Users\\agnivad\\OneDrive - Microsoft\\Agniva\\starter\\Agent_OS\\src\\core\\renderer.ts", "source_location": "L100", "weight": 1.0}, {"source": "c_users_agnivad_onedrive_microsoft_agniva_starter_agent_os_src_core_renderer_ts", "target": "core_renderer_rendervalidatorsummary", "relation": "contains", "confidence": "EXTRACTED", "source_file": "C:\\Users\\agnivad\\OneDrive - Microsoft\\Agniva\\starter\\Agent_OS\\src\\core\\renderer.ts", "source_location": "L107", "weight": 1.0}, {"source": "c_users_agnivad_onedrive_microsoft_agniva_starter_agent_os_src_core_renderer_ts", "target": "core_renderer_rendermemorystate", "relation": "contains", "confidence": "EXTRACTED", "source_file": "C:\\Users\\agnivad\\OneDrive - Microsoft\\Agniva\\starter\\Agent_OS\\src\\core\\renderer.ts", "source_location": "L123", "weight": 1.0}, {"source": "c_users_agnivad_onedrive_microsoft_agniva_starter_agent_os_src_core_renderer_ts", "target": "core_renderer_show", "relation": "contains", "confidence": "EXTRACTED", "source_file": "C:\\Users\\agnivad\\OneDrive - Microsoft\\Agniva\\starter\\Agent_OS\\src\\core\\renderer.ts", "source_location": "L131", "weight": 1.0}, {"source": "c_users_agnivad_onedrive_microsoft_agniva_starter_agent_os_src_core_renderer_ts", "target": "core_renderer_filtered", "relation": "contains", "confidence": "EXTRACTED", "source_file": "C:\\Users\\agnivad\\OneDrive - Microsoft\\Agniva\\starter\\Agent_OS\\src\\core\\renderer.ts", "source_location": "L155", "weight": 1.0}, {"source": "c_users_agnivad_onedrive_microsoft_agniva_starter_agent_os_src_core_renderer_ts", "target": "core_renderer_row", "relation": "contains", "confidence": "EXTRACTED", "source_file": "C:\\Users\\agnivad\\OneDrive - Microsoft\\Agniva\\starter\\Agent_OS\\src\\core\\renderer.ts", "source_location": "L159", "weight": 1.0}, {"source": "c_users_agnivad_onedrive_microsoft_agniva_starter_agent_os_src_core_renderer_ts", "target": "core_renderer_renderstatusopts", "relation": "contains", "confidence": "EXTRACTED", "source_file": "C:\\Users\\agnivad\\OneDrive - Microsoft\\Agniva\\starter\\Agent_OS\\src\\core\\renderer.ts", "source_location": "L167", "weight": 1.0}, {"source": "c_users_agnivad_onedrive_microsoft_agniva_starter_agent_os_src_core_renderer_ts", "target": "core_renderer_renderstatustostring", "relation": "contains", "confidence": "EXTRACTED", "source_file": "C:\\Users\\agnivad\\OneDrive - Microsoft\\Agniva\\starter\\Agent_OS\\src\\core\\renderer.ts", "source_location": "L172", "weight": 1.0}, {"source": "c_users_agnivad_onedrive_microsoft_agniva_starter_agent_os_src_core_renderer_ts", "target": "core_renderer_rendertraceopts", "relation": "contains", "confidence": "EXTRACTED", "source_file": "C:\\Users\\agnivad\\OneDrive - Microsoft\\Agniva\\starter\\Agent_OS\\src\\core\\renderer.ts", "source_location": "L227", "weight": 1.0}, {"source": "c_users_agnivad_onedrive_microsoft_agniva_starter_agent_os_src_core_renderer_ts", "target": "core_renderer_rendertracetostring", "relation": "contains", "confidence": "EXTRACTED", "source_file": "C:\\Users\\agnivad\\OneDrive - Microsoft\\Agniva\\starter\\Agent_OS\\src\\core\\renderer.ts", "source_location": "L232", "weight": 1.0}, {"source": "c_users_agnivad_onedrive_microsoft_agniva_starter_agent_os_src_core_renderer_ts", "target": "core_renderer_writereportmd", "relation": "contains", "confidence": "EXTRACTED", "source_file": "C:\\Users\\agnivad\\OneDrive - Microsoft\\Agniva\\starter\\Agent_OS\\src\\core\\renderer.ts", "source_location": "L276", "weight": 1.0}, {"source": "c_users_agnivad_onedrive_microsoft_agniva_starter_agent_os_src_core_renderer_ts", "target": "core_renderer_findmostrecentsession", "relation": "contains", "confidence": "EXTRACTED", "source_file": "C:\\Users\\agnivad\\OneDrive - Microsoft\\Agniva\\starter\\Agent_OS\\src\\core\\renderer.ts", "source_location": "L323", "weight": 1.0}, {"source": "c_users_agnivad_onedrive_microsoft_agniva_starter_agent_os_src_core_renderer_ts", "target": "core_renderer_loadsessiondashboard", "relation": "contains", "confidence": "EXTRACTED", "source_file": "C:\\Users\\agnivad\\OneDrive - Microsoft\\Agniva\\starter\\Agent_OS\\src\\core\\renderer.ts", "source_location": "L339", "weight": 1.0}, {"source": "core_renderer_healthline", "target": "core_renderer_c", "relation": "calls", "context": "call", "confidence": "EXTRACTED", "source_file": "C:\\Users\\agnivad\\OneDrive - Microsoft\\Agniva\\starter\\Agent_OS\\src\\core\\renderer.ts", "source_location": "L47", "weight": 1.0}, {"source": "core_renderer_renderpackbadge", "target": "core_renderer_c", "relation": "calls", "context": "call", "confidence": "EXTRACTED", "source_file": "C:\\Users\\agnivad\\OneDrive - Microsoft\\Agniva\\starter\\Agent_OS\\src\\core\\renderer.ts", "source_location": "L73", "weight": 1.0}, {"source": "core_renderer_rendervalidatorsummary", "target": "core_renderer_c", "relation": "calls", "context": "call", "confidence": "EXTRACTED", "source_file": "C:\\Users\\agnivad\\OneDrive - Microsoft\\Agniva\\starter\\Agent_OS\\src\\core\\renderer.ts", "source_location": "L115", "weight": 1.0}, {"source": "core_renderer_row", "target": "core_renderer_c", "relation": "calls", "context": "call", "confidence": "EXTRACTED", "source_file": "C:\\Users\\agnivad\\OneDrive - Microsoft\\Agniva\\starter\\Agent_OS\\src\\core\\renderer.ts", "source_location": "L160", "weight": 1.0}, {"source": "core_renderer_renderstatustostring", "target": "core_renderer_filtered", "relation": "calls", "context": "call", "confidence": "EXTRACTED", "source_file": "C:\\Users\\agnivad\\OneDrive - Microsoft\\Agniva\\starter\\Agent_OS\\src\\core\\renderer.ts", "source_location": "L180", "weight": 1.0}, {"source": "core_renderer_renderstatustostring", "target": "core_renderer_healthline", "relation": "calls", "context": "call", "confidence": "EXTRACTED", "source_file": "C:\\Users\\agnivad\\OneDrive - Microsoft\\Agniva\\starter\\Agent_OS\\src\\core\\renderer.ts", "source_location": "L183", "weight": 1.0}, {"source": "core_renderer_renderstatustostring", "target": "core_renderer_renderpackbadge", "relation": "calls", "context": "call", "confidence": "EXTRACTED", "source_file": "C:\\Users\\agnivad\\OneDrive - Microsoft\\Agniva\\starter\\Agent_OS\\src\\core\\renderer.ts", "source_location": "L191", "weight": 1.0}, {"source": "core_renderer_renderstatustostring", "target": "core_renderer_renderprogressbar", "relation": "calls", "context": "call", "confidence": "EXTRACTED", "source_file": "C:\\Users\\agnivad\\OneDrive - Microsoft\\Agniva\\starter\\Agent_OS\\src\\core\\renderer.ts", "source_location": "L195", "weight": 1.0}, {"source": "core_renderer_renderstatustostring", "target": "core_renderer_rendervalidatorsummary", "relation": "calls", "context": "call", "confidence": "EXTRACTED", "source_file": "C:\\Users\\agnivad\\OneDrive - Microsoft\\Agniva\\starter\\Agent_OS\\src\\core\\renderer.ts", "source_location": "L199", "weight": 1.0}, {"source": "core_renderer_renderstatustostring", "target": "core_renderer_rendermemorystate", "relation": "calls", "context": "call", "confidence": "EXTRACTED", "source_file": "C:\\Users\\agnivad\\OneDrive - Microsoft\\Agniva\\starter\\Agent_OS\\src\\core\\renderer.ts", "source_location": "L207", "weight": 1.0}, {"source": "core_renderer_renderstatustostring", "target": "core_renderer_c", "relation": "calls", "context": "call", "confidence": "EXTRACTED", "source_file": "C:\\Users\\agnivad\\OneDrive - Microsoft\\Agniva\\starter\\Agent_OS\\src\\core\\renderer.ts", "source_location": "L211", "weight": 1.0}, {"source": "core_renderer_renderstatustostring", "target": "core_renderer_row", "relation": "calls", "context": "call", "confidence": "EXTRACTED", "source_file": "C:\\Users\\agnivad\\OneDrive - Microsoft\\Agniva\\starter\\Agent_OS\\src\\core\\renderer.ts", "source_location": "L219", "weight": 1.0}, {"source": "core_renderer_rendertracetostring", "target": "core_renderer_filtered", "relation": "calls", "context": "call", "confidence": "EXTRACTED", "source_file": "C:\\Users\\agnivad\\OneDrive - Microsoft\\Agniva\\starter\\Agent_OS\\src\\core\\renderer.ts", "source_location": "L240", "weight": 1.0}, {"source": "core_renderer_rendertracetostring", "target": "core_renderer_c", "relation": "calls", "context": "call", "confidence": "EXTRACTED", "source_file": "C:\\Users\\agnivad\\OneDrive - Microsoft\\Agniva\\starter\\Agent_OS\\src\\core\\renderer.ts", "source_location": "L243", "weight": 1.0}, {"source": "core_renderer_rendertracetostring", "target": "core_renderer_healthline", "relation": "calls", "context": "call", "confidence": "EXTRACTED", "source_file": "C:\\Users\\agnivad\\OneDrive - Microsoft\\Agniva\\starter\\Agent_OS\\src\\core\\renderer.ts", "source_location": "L247", "weight": 1.0}, {"source": "core_renderer_rendertracetostring", "target": "core_renderer_renderpackbadge", "relation": "calls", "context": "call", "confidence": "EXTRACTED", "source_file": "C:\\Users\\agnivad\\OneDrive - Microsoft\\Agniva\\starter\\Agent_OS\\src\\core\\renderer.ts", "source_location": "L251", "weight": 1.0}, {"source": "core_renderer_rendertracetostring", "target": "core_renderer_row", "relation": "calls", "context": "call", "confidence": "EXTRACTED", "source_file": "C:\\Users\\agnivad\\OneDrive - Microsoft\\Agniva\\starter\\Agent_OS\\src\\core\\renderer.ts", "source_location": "L260", "weight": 1.0}, {"source": "core_renderer_writereportmd", "target": "core_renderer_filtered", "relation": "calls", "context": "call", "confidence": "EXTRACTED", "source_file": "C:\\Users\\agnivad\\OneDrive - Microsoft\\Agniva\\starter\\Agent_OS\\src\\core\\renderer.ts", "source_location": "L284", "weight": 1.0}], "raw_calls": [{"caller_nid": "core_renderer_healthline", "callee": "padEnd", "is_member_call": true, "source_file": "C:\\Users\\agnivad\\OneDrive - Microsoft\\Agniva\\starter\\Agent_OS\\src\\core\\renderer.ts", "source_location": "L48"}, {"caller_nid": "core_renderer_renderprogressbar", "callee": "max", "is_member_call": true, "source_file": "C:\\Users\\agnivad\\OneDrive - Microsoft\\Agniva\\starter\\Agent_OS\\src\\core\\renderer.ts", "source_location": "L88"}, {"caller_nid": "core_renderer_renderprogressbar", "callee": "max", "is_member_call": true, "source_file": "C:\\Users\\agnivad\\OneDrive - Microsoft\\Agniva\\starter\\Agent_OS\\src\\core\\renderer.ts", "source_location": "L89"}, {"caller_nid": "core_renderer_renderprogressbar", "callee": "min", "is_member_call": true, "source_file": "C:\\Users\\agnivad\\OneDrive - Microsoft\\Agniva\\starter\\Agent_OS\\src\\core\\renderer.ts", "source_location": "L89"}, {"caller_nid": "core_renderer_renderprogressbar", "callee": "max", "is_member_call": true, "source_file": "C:\\Users\\agnivad\\OneDrive - Microsoft\\Agniva\\starter\\Agent_OS\\src\\core\\renderer.ts", "source_location": "L90"}, {"caller_nid": "core_renderer_renderprogressbar", "callee": "round", "is_member_call": true, "source_file": "C:\\Users\\agnivad\\OneDrive - Microsoft\\Agniva\\starter\\Agent_OS\\src\\core\\renderer.ts", "source_location": "L91"}, {"caller_nid": "core_renderer_renderprogressbar", "callee": "repeat", "is_member_call": true, "source_file": "C:\\Users\\agnivad\\OneDrive - Microsoft\\Agniva\\starter\\Agent_OS\\src\\core\\renderer.ts", "source_location": "L95"}, {"caller_nid": "core_renderer_renderprogressbar", "callee": "repeat", "is_member_call": true, "source_file": "C:\\Users\\agnivad\\OneDrive - Microsoft\\Agniva\\starter\\Agent_OS\\src\\core\\renderer.ts", "source_location": "L95"}, {"caller_nid": "core_renderer_rendermemorystate", "callee": "max", "is_member_call": true, "source_file": "C:\\Users\\agnivad\\OneDrive - Microsoft\\Agniva\\starter\\Agent_OS\\src\\core\\renderer.ts", "source_location": "L124"}, {"caller_nid": "core_renderer_filtered", "callee": "filter", "is_member_call": true, "source_file": "C:\\Users\\agnivad\\OneDrive - Microsoft\\Agniva\\starter\\Agent_OS\\src\\core\\renderer.ts", "source_location": "L156"}, {"caller_nid": "core_renderer_row", "callee": "timeLabel", "is_member_call": false, "source_file": "C:\\Users\\agnivad\\OneDrive - Microsoft\\Agniva\\starter\\Agent_OS\\src\\core\\renderer.ts", "source_location": "L160"}, {"caller_nid": "core_renderer_row", "callee": "slice", "is_member_call": true, "source_file": "C:\\Users\\agnivad\\OneDrive - Microsoft\\Agniva\\starter\\Agent_OS\\src\\core\\renderer.ts", "source_location": "L161"}, {"caller_nid": "core_renderer_renderstatustostring", "callee": "now", "is_member_call": true, "source_file": "C:\\Users\\agnivad\\OneDrive - Microsoft\\Agniva\\starter\\Agent_OS\\src\\core\\renderer.ts", "source_location": "L178"}, {"caller_nid": "core_renderer_renderstatustostring", "callee": "classifyHealth", "is_member_call": false, "source_file": "C:\\Users\\agnivad\\OneDrive - Microsoft\\Agniva\\starter\\Agent_OS\\src\\core\\renderer.ts", "source_location": "L179"}, {"caller_nid": "core_renderer_renderstatustostring", "callee": "slice", "is_member_call": true, "source_file": "C:\\Users\\agnivad\\OneDrive - Microsoft\\Agniva\\starter\\Agent_OS\\src\\core\\renderer.ts", "source_location": "L180"}, {"caller_nid": "core_renderer_renderstatustostring", "callee": "push", "is_member_call": true, "source_file": "C:\\Users\\agnivad\\OneDrive - Microsoft\\Agniva\\starter\\Agent_OS\\src\\core\\renderer.ts", "source_location": "L191"}, {"caller_nid": "core_renderer_renderstatustostring", "callee": "push", "is_member_call": true, "source_file": "C:\\Users\\agnivad\\OneDrive - Microsoft\\Agniva\\starter\\Agent_OS\\src\\core\\renderer.ts", "source_location": "L195"}, {"caller_nid": "core_renderer_renderstatustostring", "callee": "fill", "is_member_call": true, "source_file": "C:\\Users\\agnivad\\OneDrive - Microsoft\\Agniva\\starter\\Agent_OS\\src\\core\\renderer.ts", "source_location": "L200"}, {"caller_nid": "core_renderer_renderstatustostring", "callee": "Array", "is_member_call": false, "source_file": "C:\\Users\\agnivad\\OneDrive - Microsoft\\Agniva\\starter\\Agent_OS\\src\\core\\renderer.ts", "source_location": "L200"}, {"caller_nid": "core_renderer_renderstatustostring", "callee": "fill", "is_member_call": true, "source_file": "C:\\Users\\agnivad\\OneDrive - Microsoft\\Agniva\\starter\\Agent_OS\\src\\core\\renderer.ts", "source_location": "L201"}, {"caller_nid": "core_renderer_renderstatustostring", "callee": "Array", "is_member_call": false, "source_file": "C:\\Users\\agnivad\\OneDrive - Microsoft\\Agniva\\starter\\Agent_OS\\src\\core\\renderer.ts", "source_location": "L201"}, {"caller_nid": "core_renderer_renderstatustostring", "callee": "fill", "is_member_call": true, "source_file": "C:\\Users\\agnivad\\OneDrive - Microsoft\\Agniva\\starter\\Agent_OS\\src\\core\\renderer.ts", "source_location": "L202"}, {"caller_nid": "core_renderer_renderstatustostring", "callee": "Array", "is_member_call": false, "source_file": "C:\\Users\\agnivad\\OneDrive - Microsoft\\Agniva\\starter\\Agent_OS\\src\\core\\renderer.ts", "source_location": "L202"}, {"caller_nid": "core_renderer_renderstatustostring", "callee": "push", "is_member_call": true, "source_file": "C:\\Users\\agnivad\\OneDrive - Microsoft\\Agniva\\starter\\Agent_OS\\src\\core\\renderer.ts", "source_location": "L204"}, {"caller_nid": "core_renderer_renderstatustostring", "callee": "push", "is_member_call": true, "source_file": "C:\\Users\\agnivad\\OneDrive - Microsoft\\Agniva\\starter\\Agent_OS\\src\\core\\renderer.ts", "source_location": "L207"}, {"caller_nid": "core_renderer_renderstatustostring", "callee": "push", "is_member_call": true, "source_file": "C:\\Users\\agnivad\\OneDrive - Microsoft\\Agniva\\starter\\Agent_OS\\src\\core\\renderer.ts", "source_location": "L209"}, {"caller_nid": "core_renderer_renderstatustostring", "callee": "ageLabel", "is_member_call": false, "source_file": "C:\\Users\\agnivad\\OneDrive - Microsoft\\Agniva\\starter\\Agent_OS\\src\\core\\renderer.ts", "source_location": "L209"}, {"caller_nid": "core_renderer_renderstatustostring", "callee": "push", "is_member_call": true, "source_file": "C:\\Users\\agnivad\\OneDrive - Microsoft\\Agniva\\starter\\Agent_OS\\src\\core\\renderer.ts", "source_location": "L211"}, {"caller_nid": "core_renderer_renderstatustostring", "callee": "String", "is_member_call": false, "source_file": "C:\\Users\\agnivad\\OneDrive - Microsoft\\Agniva\\starter\\Agent_OS\\src\\core\\renderer.ts", "source_location": "L211"}, {"caller_nid": "core_renderer_renderstatustostring", "callee": "push", "is_member_call": true, "source_file": "C:\\Users\\agnivad\\OneDrive - Microsoft\\Agniva\\starter\\Agent_OS\\src\\core\\renderer.ts", "source_location": "L213"}, {"caller_nid": "core_renderer_renderstatustostring", "callee": "push", "is_member_call": true, "source_file": "C:\\Users\\agnivad\\OneDrive - Microsoft\\Agniva\\starter\\Agent_OS\\src\\core\\renderer.ts", "source_location": "L214"}, {"caller_nid": "core_renderer_renderstatustostring", "callee": "push", "is_member_call": true, "source_file": "C:\\Users\\agnivad\\OneDrive - Microsoft\\Agniva\\starter\\Agent_OS\\src\\core\\renderer.ts", "source_location": "L217"}, {"caller_nid": "core_renderer_renderstatustostring", "callee": "push", "is_member_call": true, "source_file": "C:\\Users\\agnivad\\OneDrive - Microsoft\\Agniva\\starter\\Agent_OS\\src\\core\\renderer.ts", "source_location": "L218"}, {"caller_nid": "core_renderer_renderstatustostring", "callee": "push", "is_member_call": true, "source_file": "C:\\Users\\agnivad\\OneDrive - Microsoft\\Agniva\\starter\\Agent_OS\\src\\core\\renderer.ts", "source_location": "L219"}, {"caller_nid": "core_renderer_renderstatustostring", "callee": "join", "is_member_call": true, "source_file": "C:\\Users\\agnivad\\OneDrive - Microsoft\\Agniva\\starter\\Agent_OS\\src\\core\\renderer.ts", "source_location": "L222"}, {"caller_nid": "core_renderer_rendertracetostring", "callee": "now", "is_member_call": true, "source_file": "C:\\Users\\agnivad\\OneDrive - Microsoft\\Agniva\\starter\\Agent_OS\\src\\core\\renderer.ts", "source_location": "L238"}, {"caller_nid": "core_renderer_rendertracetostring", "callee": "classifyHealth", "is_member_call": false, "source_file": "C:\\Users\\agnivad\\OneDrive - Microsoft\\Agniva\\starter\\Agent_OS\\src\\core\\renderer.ts", "source_location": "L239"}, {"caller_nid": "core_renderer_rendertracetostring", "callee": "slice", "is_member_call": true, "source_file": "C:\\Users\\agnivad\\OneDrive - Microsoft\\Agniva\\starter\\Agent_OS\\src\\core\\renderer.ts", "source_location": "L241"}, {"caller_nid": "core_renderer_rendertracetostring", "callee": "repeat", "is_member_call": true, "source_file": "C:\\Users\\agnivad\\OneDrive - Microsoft\\Agniva\\starter\\Agent_OS\\src\\core\\renderer.ts", "source_location": "L243"}, {"caller_nid": "core_renderer_rendertracetostring", "callee": "slice", "is_member_call": true, "source_file": "C:\\Users\\agnivad\\OneDrive - Microsoft\\Agniva\\starter\\Agent_OS\\src\\core\\renderer.ts", "source_location": "L247"}, {"caller_nid": "core_renderer_rendertracetostring", "callee": "push", "is_member_call": true, "source_file": "C:\\Users\\agnivad\\OneDrive - Microsoft\\Agniva\\starter\\Agent_OS\\src\\core\\renderer.ts", "source_location": "L251"}, {"caller_nid": "core_renderer_rendertracetostring", "callee": "push", "is_member_call": true, "source_file": "C:\\Users\\agnivad\\OneDrive - Microsoft\\Agniva\\starter\\Agent_OS\\src\\core\\renderer.ts", "source_location": "L253"}, {"caller_nid": "core_renderer_rendertracetostring", "callee": "push", "is_member_call": true, "source_file": "C:\\Users\\agnivad\\OneDrive - Microsoft\\Agniva\\starter\\Agent_OS\\src\\core\\renderer.ts", "source_location": "L256"}, {"caller_nid": "core_renderer_rendertracetostring", "callee": "push", "is_member_call": true, "source_file": "C:\\Users\\agnivad\\OneDrive - Microsoft\\Agniva\\starter\\Agent_OS\\src\\core\\renderer.ts", "source_location": "L259"}, {"caller_nid": "core_renderer_rendertracetostring", "callee": "push", "is_member_call": true, "source_file": "C:\\Users\\agnivad\\OneDrive - Microsoft\\Agniva\\starter\\Agent_OS\\src\\core\\renderer.ts", "source_location": "L260"}, {"caller_nid": "core_renderer_rendertracetostring", "callee": "push", "is_member_call": true, "source_file": "C:\\Users\\agnivad\\OneDrive - Microsoft\\Agniva\\starter\\Agent_OS\\src\\core\\renderer.ts", "source_location": "L263"}, {"caller_nid": "core_renderer_rendertracetostring", "callee": "ageLabel", "is_member_call": false, "source_file": "C:\\Users\\agnivad\\OneDrive - Microsoft\\Agniva\\starter\\Agent_OS\\src\\core\\renderer.ts", "source_location": "L267"}, {"caller_nid": "core_renderer_rendertracetostring", "callee": "join", "is_member_call": true, "source_file": "C:\\Users\\agnivad\\OneDrive - Microsoft\\Agniva\\starter\\Agent_OS\\src\\core\\renderer.ts", "source_location": "L271"}, {"caller_nid": "core_renderer_writereportmd", "callee": "classifyHealth", "is_member_call": false, "source_file": "C:\\Users\\agnivad\\OneDrive - Microsoft\\Agniva\\starter\\Agent_OS\\src\\core\\renderer.ts", "source_location": "L282"}, {"caller_nid": "core_renderer_writereportmd", "callee": "join", "is_member_call": true, "source_file": "C:\\Users\\agnivad\\OneDrive - Microsoft\\Agniva\\starter\\Agent_OS\\src\\core\\renderer.ts", "source_location": "L284"}, {"caller_nid": "core_renderer_writereportmd", "callee": "map", "is_member_call": true, "source_file": "C:\\Users\\agnivad\\OneDrive - Microsoft\\Agniva\\starter\\Agent_OS\\src\\core\\renderer.ts", "source_location": "L284"}, {"caller_nid": "core_renderer_writereportmd", "callee": "join", "is_member_call": true, "source_file": "C:\\Users\\agnivad\\OneDrive - Microsoft\\Agniva\\starter\\Agent_OS\\src\\core\\renderer.ts", "source_location": "L288"}, {"caller_nid": "core_renderer_writereportmd", "callee": "toISOString", "is_member_call": true, "source_file": "C:\\Users\\agnivad\\OneDrive - Microsoft\\Agniva\\starter\\Agent_OS\\src\\core\\renderer.ts", "source_location": "L295"}, {"caller_nid": "core_renderer_writereportmd", "callee": "replace", "is_member_call": true, "source_file": "C:\\Users\\agnivad\\OneDrive - Microsoft\\Agniva\\starter\\Agent_OS\\src\\core\\renderer.ts", "source_location": "L313"}, {"caller_nid": "core_renderer_writereportmd", "callee": "sessionDashboardPath", "is_member_call": false, "source_file": "C:\\Users\\agnivad\\OneDrive - Microsoft\\Agniva\\starter\\Agent_OS\\src\\core\\renderer.ts", "source_location": "L313"}, {"caller_nid": "core_renderer_writereportmd", "callee": "writeFileSync", "is_member_call": false, "source_file": "C:\\Users\\agnivad\\OneDrive - Microsoft\\Agniva\\starter\\Agent_OS\\src\\core\\renderer.ts", "source_location": "L317"}, {"caller_nid": "core_renderer_findmostrecentsession", "callee": "join", "is_member_call": false, "source_file": "C:\\Users\\agnivad\\OneDrive - Microsoft\\Agniva\\starter\\Agent_OS\\src\\core\\renderer.ts", "source_location": "L324"}, {"caller_nid": "core_renderer_findmostrecentsession", "callee": "runtimeDir", "is_member_call": false, "source_file": "C:\\Users\\agnivad\\OneDrive - Microsoft\\Agniva\\starter\\Agent_OS\\src\\core\\renderer.ts", "source_location": "L324"}, {"caller_nid": "core_renderer_findmostrecentsession", "callee": "existsSync", "is_member_call": false, "source_file": "C:\\Users\\agnivad\\OneDrive - Microsoft\\Agniva\\starter\\Agent_OS\\src\\core\\renderer.ts", "source_location": "L325"}, {"caller_nid": "core_renderer_findmostrecentsession", "callee": "readdirSync", "is_member_call": false, "source_file": "C:\\Users\\agnivad\\OneDrive - Microsoft\\Agniva\\starter\\Agent_OS\\src\\core\\renderer.ts", "source_location": "L326"}, {"caller_nid": "core_renderer_findmostrecentsession", "callee": "sort", "is_member_call": true, "source_file": "C:\\Users\\agnivad\\OneDrive - Microsoft\\Agniva\\starter\\Agent_OS\\src\\core\\renderer.ts", "source_location": "L329"}, {"caller_nid": "core_renderer_findmostrecentsession", "callee": "map", "is_member_call": true, "source_file": "C:\\Users\\agnivad\\OneDrive - Microsoft\\Agniva\\starter\\Agent_OS\\src\\core\\renderer.ts", "source_location": "L329"}, {"caller_nid": "core_renderer_loadsessiondashboard", "callee": "sessionDashboardPath", "is_member_call": false, "source_file": "C:\\Users\\agnivad\\OneDrive - Microsoft\\Agniva\\starter\\Agent_OS\\src\\core\\renderer.ts", "source_location": "L343"}, {"caller_nid": "core_renderer_loadsessiondashboard", "callee": "existsSync", "is_member_call": false, "source_file": "C:\\Users\\agnivad\\OneDrive - Microsoft\\Agniva\\starter\\Agent_OS\\src\\core\\renderer.ts", "source_location": "L344"}, {"caller_nid": "core_renderer_loadsessiondashboard", "callee": "parse", "is_member_call": true, "source_file": "C:\\Users\\agnivad\\OneDrive - Microsoft\\Agniva\\starter\\Agent_OS\\src\\core\\renderer.ts", "source_location": "L346"}, {"caller_nid": "core_renderer_loadsessiondashboard", "callee": "readFileSync", "is_member_call": false, "source_file": "C:\\Users\\agnivad\\OneDrive - Microsoft\\Agniva\\starter\\Agent_OS\\src\\core\\renderer.ts", "source_location": "L346"}]}